PurpleMicroStar/BasicConst.py
PurpleMicroStar/BasicMech.py
PurpleMicroStar/GravitationalWave.py
PurpleMicroStar/MultiBody.py
PurpleMicroStar/Sample.py
PurpleMicroStar/StarBody.py
PurpleMicroStar/__init__.py
PurpleMicroStar/exampledata/Multibody-3.csv
PurpleMicroStar/exampledata/Multibody-6.csv
PurpleMicroStar-1.3.0.dist-info/LICENSE.TXT
PurpleMicroStar-1.3.0.dist-info/METADATA
PurpleMicroStar-1.3.0.dist-info/WHEEL
PurpleMicroStar-1.3.0.dist-info/entry_points.txt
PurpleMicroStar-1.3.0.dist-info/top_level.txt
PurpleMicroStar-1.3.0.dist-info/RECORD
