Metadata-Version: 2.1
Name: PurpleMicroStar
Version: 1.3.0
Summary: Universe is waiting for us to explore! 
Home-page: https://airscker.github.io/Purple-Micro-Star/
Author: Airscker/Yufeng Wang
Author-email: airscker@gmail.com
License: GPL-3.0
Keywords: Multibody Motion,Gravitational Wave,Science
Platform: UNKNOWN
Classifier: Development Status :: 5 - Production/Stable
Classifier: Intended Audience :: Developers
Classifier: Topic :: Software Development :: Build Tools
Classifier: License :: OSI Approved :: GNU Lesser General Public License v3 (LGPLv3)
Classifier: Programming Language :: Python :: 3
Classifier: Programming Language :: Python :: 3.7
Classifier: Programming Language :: Python :: 3.8
Classifier: Programming Language :: Python :: 3.9
Classifier: Programming Language :: Python :: 3.10
Classifier: Programming Language :: Python :: 3 :: Only
Classifier: Operating System :: Microsoft :: Windows
Requires-Python: >=3.5, <4
License-File: LICENSE.TXT
Requires-Dist: numpy
Requires-Dist: click
Requires-Dist: tqdm
Requires-Dist: prettytable
Requires-Dist: matplotlib
